Metadata-Version: 2.4
Name: workforce
Version: 1.1.18
Summary: Run bash commands with python multiprocessing. Includes a Tkinter GUI for workflow editing.
Author-email: Theo Portlock <zn.tportlock@gmail.com>
License: MIT
Project-URL: Homepage, https://github.com/theoportlock/workforce
Classifier: Development Status :: 2 - Pre-Alpha
Classifier: Intended Audience :: Developers
Classifier: License :: OSI Approved :: MIT License
Classifier: Natural Language :: English
Classifier: Programming Language :: Python :: 3
Classifier: Programming Language :: Python :: 3.6
Classifier: Programming Language :: Python :: 3.7
Classifier: Programming Language :: Python :: 3.8
Classifier: Programming Language :: Python :: 3.9
Classifier: Programming Language :: Python :: 3.10
Classifier: Programming Language :: Python :: 3.11
Classifier: Programming Language :: Python :: 3.12
Requires-Python: >=3.6
License-File: LICENSE
License-File: AUTHORS.rst
Requires-Dist: networkx
Requires-Dist: flask
Requires-Dist: flask-socketio
Requires-Dist: python-socketio
Requires-Dist: websocket-client
Requires-Dist: requests
Requires-Dist: platformdirs
Provides-Extra: dev
Requires-Dist: pytest; extra == "dev"
Requires-Dist: pytest-cov; extra == "dev"
Requires-Dist: ruff; extra == "dev"
Requires-Dist: mypy; extra == "dev"
Dynamic: license-file
